[{"description":"Acme Directory system","owner":{"type":"IDENTITY","id":"2c9180838366dc6001836ac682010274","name":"Trainee"},"cluster":{"type":"CLUSTER","id":"2c9180888362026701836abf0760650b","name":"VA Cluster"},"accountCorrelationConfig":{"type":"ACCOUNT_CORRELATION_CONFIG","id":"5029765e22ab47f29419c912194ae615","name":"OpenLDAP Template Account Correlation Config"},"accountCorrelationRule":null,"managerCorrelationMapping":null,"managerCorrelationRule":null,"beforeProvisioningRule":null,"schemas":[{"type":"CONNECTOR_SCHEMA","id":"2c918087837ac52301837ad1b3500099","name":"account"},{"type":"CONNECTOR_SCHEMA","id":"2c918087837ac52301837ad1b350009a","name":"group"}],"passwordPolicies":null,"features":["MANAGER_LOOKUP","GROUP_PROVISIONING","PASSWORD","SYNC_PROVISIONING","SEARCH","PROVISIONING","AUTHENTICATE"],"type":"OpenLDAP - Direct","connector":"openldap-angularsc","connectorClass":"sailpoint.connector.LDAPConnector","connectorAttributes":{"healthCheckTimeout":30,"filterString":null,"groupMemberAttribute":"uniqueMember","pageSize":"100","connectionType":"direct","posixGroup_Member_Attribute":null,"enableNetGroups":false,"password":"1:YR8nLSdlkHRIaILSPOgM+JUCzgS6hstzoXaZR3255Rqfq40k0njgTKYewDwfAWvfJLdfMlMeCR3o\nksRuZAMDwM0oJQtaw8wyKoKvv6HSkrpfgKgGQJYTMOmHbhSF7YiShz5tEtvzTM9CVh42G0sYmfpA\npzq7HDNpA586QsqLB9QG7TlgwMTNeswU2TkE3SehVBV5rqQZXnLk/HPb+PwxLATPdodi47IhORO6\nDtVkm4nsY1WMc7GlBbuevJIMHlrZU1Vs23AQTIuN7ZZO/fahMpTn6QYa/n8jcqkOAw2dOb7BnK5l\nTPi2YHXf4/gcOuMeeydwGnUlxy6Edsjxak7AQgqUh2Temnq0qkOAnP13RAqlQ9VywhmCtEYtS4ML\nUbl8NNLdHTBp4YmWfddx9a+D5SW3lxz3K7bt0+3oFIddj2Wy9RiwCi6VbNCWX1+ssnSpFVVRAgbO\nvOoUET/owG0FrAiU5eIG/vTbKvwMq0fCUzh/jf4oVwgpRgD9FqP2B7u6OR23D3la+BNyglURQ2uo\ng5xTLOsJACwBFc6kFRNeRqizjtDdR4wCBrSqQgeH4SBK","charsToEscapeWhileProvisioning":"/","host":"10.0.0.2","authorizationType":"simple","cloudExternalId":"327874","keystore":null,"nisNetGroupTriple_Member_Attribute":null,"group":"[searchScope:SUBTREE, searchDN:ou\u003dgroups,dc\u003dexample,dc\u003dcom, iterateSearchFilter:, filterString:]","cloudUniqueSearchDN":null,"group.filterString":null,"enablePosixGroups":false,"searchScope":"SUBTREE","group.searchScope":"SUBTREE","iterateModeOverride":"DEFAULT","skipBackslashInFilter":"true","iterateSearchFilter":null,"useSSL":false,"formPath":null,"cloudCacheUpdate":1664379357564,"port":"389","charsToEscapeAtStartInDN":" #","connectorName":"OpenLDAP","nisNetGroupTriple_Brace_Override":null,"charsToEscapeInDN":",+\\\"\u003c\u003e;","since":"2022-09-26T17:25:23.454248Z","status":"SOURCE_STATE_HEALTHY","authSearchAttributes":["cn","uid","mail"],"searchDN":"ou\u003dusers,dc\u003dexample,dc\u003dcom","group.searchDN":"ou\u003dgroups,dc\u003dexample,dc\u003dcom","cloudAuthEnabled":true,"deltaAggregation":null,"groupEntitlementAttr":"groups","group.iterateSearchFilter":null,"groupMemberFilterString":null,"deleteThresholdPercentage":10,"passwordAttr":"userPassword","templateApplication":"OpenLDAP Template","convertHexToCharacter":"true","healthy":true,"charsToEscapeAtEndInDN":" ","cloudDisplayName":"Directory","groupMemberSearchDN":"ou\u003dgroups,dc\u003dexample,dc\u003dcom","user":"cn\u003dadmin,dc\u003dexample,dc\u003dcom","beforeProvisioningRule":null},"deleteThreshold":10,"authoritative":false,"healthy":true,"status":"SOURCE_STATE_HEALTHY","since":"2022-09-26T17:25:23.454248Z","connectorId":"openldap","connectorName":"OpenLDAP","connectionType":"direct","connectorImplementationId":"openldap","managementWorkgroup":null,"id":"2c918087837ac52301837ad1b34f0098","name":"Directory","created":"2022-09-26T17:21:46.832Z","modified":"2022-09-28T15:35:57.564Z"},{"description":"Employees source extract","owner":{"type":"IDENTITY","id":"2c9180838366dc6001836ac682010274","name":"Trainee"},"cluster":null,"accountCorrelationConfig":null,"accountCorrelationRule":null,"managerCorrelationMapping":{"identityAttributeName":"name","accountAttributeName":"manager"},"managerCorrelationRule":null,"beforeProvisioningRule":null,"schemas":[{"type":"CONNECTOR_SCHEMA","id":"2c9180888362026701837aa71f2e1d20","name":"account"},{"type":"CONNECTOR_SCHEMA","id":"2c9180888362026701837aa71f2e1d21","name":"group"}],"passwordPolicies":null,"features":["NO_RANDOM_ACCESS","DIRECT_PERMISSIONS","DISCOVER_SCHEMA"],"type":"DelimitedFile","connector":"delimited-file-angularsc","connectorClass":"sailpoint.connector.DelimitedFileConnector","connectorAttributes":{"mergeColumns":["id","name","givenName","familyName","manager","email","locale","location","department","title","costCenter","status","comments","startDate","endDate","type","country","employeeNumber","middleName","phoneNumber","preferredLanguage","secondaryEmail","secondaryPhoneNumber"],"group.mergeRows":true,"group.delimiter":",","mergeRows":true,"group.filetransport":"local","partitionMode":"disabled","connectionType":"file","group.host":"local","group.indexColumn":"id","file":"/tmp/source-account-2c9180888362026701837aa71f2e1d1f1817413683444693957.csv","delimiter":",","deltaAggregation":null,"host":"local","cloudExternalId":"327860","indexColumns":["id"],"cloudIdentityProfileName":"Employees","group.mergeColumns":["entitlements","groups","permissions"],"hasHeader":true,"filterEmptyRecords":true,"filetransport":"local","deleteThresholdPercentage":10,"group.filterEmptyRecords":true,"group.hasHeader":true,"group.partitionMode":"disabled","cloudAuthoritativeSourcePrecedence":20,"formPath":null,"group.columnNames":["id","name","displayName","created","description","modified","entitlements","groups","permissions"],"templateApplication":"DelimitedFile Template","indexColumn":"id","healthy":true,"cloudDisplayName":"Employees","connectorName":"Delimited File","beforeProvisioningRule":null,"cloudOriginalApplicationType":"Delimited File","since":"2022-09-26T16:35:16.398Z","status":"SOURCE_STATE_HEALTHY"},"deleteThreshold":10,"authoritative":true,"healthy":true,"status":"SOURCE_STATE_HEALTHY","since":"2022-09-26T16:35:16.398Z","connectorId":"delimited-file","connectorName":"Delimited File","connectionType":"file","connectorImplementationId":"delimited-file","managementWorkgroup":null,"id":"2c9180888362026701837aa71f2e1d1f","name":"Employees","created":"2022-09-26T16:35:16.398Z","modified":"2022-09-28T15:38:15.913Z"},{"description":"Special Administrators","owner":{"type":"IDENTITY","id":"accb2420059c414cb147bd3866f95339","name":"SailPoint Services"},"cluster":null,"accountCorrelationConfig":{"type":"ACCOUNT_CORRELATION_CONFIG","id":"49ce07153172433d9d455347a37f9fbc","name":"Generic Account Correlation Config"},"accountCorrelationRule":null,"managerCorrelationMapping":{"identityAttributeName":"name","accountAttributeName":"manager"},"managerCorrelationRule":null,"beforeProvisioningRule":null,"schemas":[{"type":"CONNECTOR_SCHEMA","id":"2c91808a8361e1a401836ab3924d65dc","name":"account"},{"type":"CONNECTOR_SCHEMA","id":"2c91808a8361e1a401836ab3924d65dd","name":"group"}],"passwordPolicies":null,"features":["NO_RANDOM_ACCESS","DIRECT_PERMISSIONS","DISCOVER_SCHEMA"],"type":"DelimitedFile","connector":"delimited-file-angularsc","connectorClass":"sailpoint.connector.DelimitedFileConnector","connectorAttributes":{"mergeColumns":["groups","secondaryEmail","secondaryPhoneNumber"],"group.mergeRows":true,"group.delimiter":",","mergeRows":true,"group.filetransport":"local","partitionMode":"disabled","connectionType":"file","group.host":"local","group.indexColumn":"id","file":"/tmp/source-account-2c91808a8361e1a401836ab3924c65db11292533032033796461.csv","delimiter":",","deltaAggregation":null,"host":"local","cloudExternalId":"326014","commentCharacter":"#","cloudIdentityProfileName":"IDN Admins","group.mergeColumns":["entitlements","groups","permissions"],"hasHeader":true,"filterEmptyRecords":true,"filetransport":"local","deleteThresholdPercentage":10,"group.filterEmptyRecords":true,"group.hasHeader":true,"group.partitionMode":"disabled","cloudAuthoritativeSourcePrecedence":10,"formPath":null,"group.columnNames":["id","name","displayName","created","description","modified","entitlements","groups","permissions"],"templateApplication":"DelimitedFile Template","group.file":"/var/lib/identityiq_workspace/8b1d978e-a295-47a3-9ec4-c5e5f50faa37-groups.csv","indexColumn":"id","healthy":true,"cloudDisplayName":"IDN Admins","connectorName":"Generic","beforeProvisioningRule":null,"cloudOriginalApplicationType":"Generic","since":"2022-09-23T14:14:56.844Z","status":"SOURCE_STATE_HEALTHY"},"deleteThreshold":10,"authoritative":true,"healthy":true,"status":"SOURCE_STATE_HEALTHY","since":"2022-09-23T14:14:56.844Z","connectorId":"generic","connectorName":"Generic","connectionType":"file","connectorImplementationId":"delimited-file","managementWorkgroup":null,"id":"2c91808a8361e1a401836ab3924c65db","name":"IDN Admins","created":"2022-09-23T14:14:56.844Z","modified":"2022-09-23T14:35:37.414Z"}]